TFdisc/__init__.py
TFdisc/gen_model.py
TFdisc/grn.py
TFdisc/imputation.py
TFdisc/pre_model.py
TFdisc/train_model.py
TFdisc-1.2.0.dist-info/LICENSE
TFdisc-1.2.0.dist-info/METADATA
TFdisc-1.2.0.dist-info/WHEEL
TFdisc-1.2.0.dist-info/top_level.txt
TFdisc-1.2.0.dist-info/RECORD
