Metadata-Version: 2.1
Name: TFdisc
Version: 1.2.0
Summary: in silico transcription factor (TF) perturbation simulator
Home-page: https://github.com/ocean-debug/TFdisc
Author: Haiyang Wang
Author-email: your.email@example.com
Classifier: Programming Language :: Python :: 3
Classifier: License :: OSI Approved :: MIT License
Classifier: Operating System :: OS Independent
Requires-Python: >=3.6
License-File: LICENSE
Requires-Dist: numpy
Requires-Dist: pandas
Requires-Dist: scikit-learn
Requires-Dist: arboreto
Requires-Dist: tqdm
Requires-Dist: dask
Requires-Dist: rpy2
Requires-Dist: scanpy
